glook/GLook.py
glook/__init__.py
glook/cli.py
glook/pages/1_General_Data_Insights.py
glook/pages/2_Univariate_Analysis.py
glook/pages/3_Bivariate_Analysis.py
glook/pages/4_Trivariate_Analysis.py
glook-0.1.6.dist-info/METADATA
glook-0.1.6.dist-info/WHEEL
glook-0.1.6.dist-info/entry_points.txt
glook-0.1.6.dist-info/top_level.txt
glook-0.1.6.dist-info/RECORD
