Metadata-Version: 2.1
Name: glook
Version: 0.1.6
Summary: Auto EDA.
Home-page: https://github.com/gaurang157/glook
Author: Gaurang Ingle
Author-email: gaurang.ingle@gmail.com
Maintainer: Gaurang Ingle, Sharat Chandra Manikonda
Maintainer-email: manikondasharat@gmail.com
License: MIT
Project-URL: Bug Reports, https://github.com/gaurang157/glook/issues
Project-URL: Source, https://github.com/gaurang157/glook
Project-URL: Documentation, https://github.com/gaurang157/glook/blob/main/README.md
Project-URL: Say Thanks!, https://github.com/gaurang157/glook/issues/new?assignees=&labels=&template=thanks.yml
Keywords: AutoEDA,Exploratory Data Analysis,Data Visualization,GUI,CLI,Python,Streamlit,CLI interface,UI interface
Classifier: Programming Language :: Python :: 3
Classifier: Operating System :: OS Independent
Classifier: Development Status :: 4 - Beta
Classifier: Intended Audience :: End Users/Desktop
Classifier: Intended Audience :: Developers
Classifier: Intended Audience :: Education
Classifier: Natural Language :: English
Classifier: Topic :: Scientific/Engineering :: Information Analysis
Classifier: Topic :: Scientific/Engineering :: Visualization
Classifier: License :: OSI Approved :: MIT License
Classifier: Topic :: Software Development :: Libraries :: Application Frameworks
Classifier: Topic :: Software Development :: User Interfaces
Classifier: Topic :: Utilities
Requires-Python: >=3.8
Requires-Dist: matplotlib ==3.7.4
Requires-Dist: numpy ==1.24.4
Requires-Dist: pandas ==2.0.3
Requires-Dist: plotly ==5.19.0
Requires-Dist: scipy ==1.10.0
Requires-Dist: seaborn ==0.13.2
Requires-Dist: statsmodels ==0.14.1
Requires-Dist: streamlit ==1.31.1
Requires-Dist: wordcloud ==1.9.3
Requires-Dist: openpyxl ==3.1.2
